TSAnalyzer/__init__.py
TSAnalyzer/contoller.py
TSAnalyzer/utils.py
TSAnalyzer/window.py
TSAnalyzer/algorithms/__init__.py
TSAnalyzer/algorithms/date.py
TSAnalyzer/algorithms/fit.py
TSAnalyzer/algorithms/l1extensive.py
TSAnalyzer/models/__init__.py
TSAnalyzer/models/offsets.py
TSAnalyzer/models/reader.py
TSAnalyzer/resources/style.qss
TSAnalyzer/resources/images/back.png
TSAnalyzer/resources/images/expdecay.png
TSAnalyzer/resources/images/expdecay_b.png
TSAnalyzer/resources/images/forward.png
TSAnalyzer/resources/images/home.png
TSAnalyzer/resources/images/icon.ico
TSAnalyzer/resources/images/icon.png
TSAnalyzer/resources/images/logdecay.png
TSAnalyzer/resources/images/logdecay_b.png
TSAnalyzer/resources/images/offset.png
TSAnalyzer/resources/images/options.png
TSAnalyzer/resources/images/pan.png
TSAnalyzer/resources/images/save.png
TSAnalyzer/resources/images/subplots.png
TSAnalyzer/resources/images/trendchange.png
TSAnalyzer/resources/images/zoom.png
TSAnalyzer/resources/ui/about.ui
TSAnalyzer/resources/ui/analysis_timeseries.ui
TSAnalyzer/resources/ui/batch.ui
TSAnalyzer/resources/ui/date.ui
TSAnalyzer/resources/ui/discontinuity.ui
TSAnalyzer/resources/ui/event_decay.ui
TSAnalyzer/resources/ui/header.ui
TSAnalyzer/thread/__init__.py
TSAnalyzer/thread/fit_thread.py
TSAnalyzer/thread/l1_thread.py
TSAnalyzer/thread/plot_thread.py
TSAnalyzer/widgets/__init__.py
TSAnalyzer/widgets/about_dialog.py
TSAnalyzer/widgets/analysis_dockwidget.py
TSAnalyzer/widgets/batch_widget.py
TSAnalyzer/widgets/console_dock.py
TSAnalyzer/widgets/date_dialog.py
TSAnalyzer/widgets/discontinuity_dock.py
TSAnalyzer/widgets/discontinuity_dockwidget.py
TSAnalyzer/widgets/figure.py
TSAnalyzer/widgets/file_dockwidget.py
TSAnalyzer/widgets/header_widget.py
TSAnalyzer/widgets/timeseries_figure.py
TSAnalyzer/widgets/timeseries_toolbar.py
TSAnalyzer/widgets/timeseries_widget.py
TSAnalyzer-2.0.1.dist-info/DESCRIPTION.rst
TSAnalyzer-2.0.1.dist-info/METADATA
TSAnalyzer-2.0.1.dist-info/RECORD
TSAnalyzer-2.0.1.dist-info/WHEEL
TSAnalyzer-2.0.1.dist-info/entry_points.txt
TSAnalyzer-2.0.1.dist-info/metadata.json
TSAnalyzer-2.0.1.dist-info/top_level.txt
