Metadata-Version: 2.0
Name: TSAnalyzer
Version: 2.0.1
Summary: Python GNSS Time Series Analysis and Visualization
Home-page: https://github.com/wudingcheng/tsanalyzer
Author: WU Dingcheng
Author-email: wudingcheng14@mails.ucas.ac.cn
License: GPL v3
Platform: UNKNOWN
Requires-Dist: cvxopt
Requires-Dist: cvxpy
Requires-Dist: matplotlib
Requires-Dist: numpy
Requires-Dist: pandas
Requires-Dist: qtpy
